{
  "timestamp": "2026-01-09T09:48:59.569489",
  "total_trades": 8,
  "ml_take_count": 7,
  "ml_skip_count": 1,
  "original_win_rate": 0.875,
  "original_total_profit": 10.780000000000001,
  "ml_win_rate": 1.0,
  "ml_total_profit": 11.179999999999998,
  "win_rate_improvement": 0.125,
  "profit_improvement": 0.3999999999999968,
  "model_info": {
    "model_type": "RandomForestClassifier",
    "confidence_threshold": 0.6,
    "n_features": 49,
    "top_5_features": [
      {
        "feature": "minus_di",
        "importance": 0.1875
      },
      {
        "feature": "session_sydney",
        "importance": 0.16666666666666666
      },
      {
        "feature": "session_tokyo",
        "importance": 0.1488095238095238
      },
      {
        "feature": "plus_di",
        "importance": 0.08630952380952381
      },
      {
        "feature": "at_swing_high",
        "importance": 0.07589285714285715
      }
    ]
  }
}